crystalball/__init__.py
crystalball/budget.py
crystalball/crystalball.py
crystalball/filtering.py
crystalball/logger_init.py
crystalball/ms.py
crystalball/region.py
crystalball/wsclean.py
crystalball-0.4.1.dist-info/LICENSE
crystalball-0.4.1.dist-info/METADATA
crystalball-0.4.1.dist-info/WHEEL
crystalball-0.4.1.dist-info/entry_points.txt
crystalball-0.4.1.dist-info/top_level.txt
crystalball-0.4.1.dist-info/RECORD
