Metadata-Version: 2.1
Name: crystalball
Version: 0.4.1
Summary: Predicts visibilities from a parameterised sky model
Home-page: https://github.com/caracal-pipeline/crystalball
Author: Paolo Serra and others
Author-email: paolo80serra@gmail.com
License: GNU GPL v2
Classifier: Development Status :: 3 - Alpha
Classifier: Intended Audience :: Science/Research
Classifier: License :: OSI Approved :: GNU General Public License v2 (GPLv2)
Classifier: Operating System :: POSIX :: Linux
Classifier: Programming Language :: Python
Classifier: Topic :: Scientific/Engineering :: Astronomy
Requires-Python: >=3.7
License-File: LICENSE
Requires-Dist: codex-africanus[dask]>=0.3.1
Requires-Dist: dask-ms>=0.2.6
Requires-Dist: loguru
Requires-Dist: regions
Requires-Dist: psutil
Provides-Extra: testing
Requires-Dist: pytest; extra == "testing"
Requires-Dist: pytest-flake8; extra == "testing"
